reliablegpt/Alerting.py
reliablegpt/IndividualRequest.py
reliablegpt/Model.py
reliablegpt/__init__.py
reliablegpt/main.py
reliableGPT-0.3.0.dist-info/LICENSE
reliableGPT-0.3.0.dist-info/METADATA
reliableGPT-0.3.0.dist-info/WHEEL
reliableGPT-0.3.0.dist-info/top_level.txt
reliableGPT-0.3.0.dist-info/RECORD
